boostedblob/__init__.py
boostedblob/__main__.py
boostedblob/_recover.py
boostedblob/azure_auth.py
boostedblob/boost.py
boostedblob/cli.py
boostedblob/copying.py
boostedblob/delete.py
boostedblob/globals.py
boostedblob/google_auth.py
boostedblob/listing.py
boostedblob/path.py
boostedblob/path_registry.py
boostedblob/py.typed
boostedblob/read.py
boostedblob/request.py
boostedblob/share.py
boostedblob/syncing.py
boostedblob/write.py
boostedblob/xml.py
boostedblob-1.0.0.dist-info/entry_points.txt
boostedblob-1.0.0.dist-info/WHEEL
boostedblob-1.0.0.dist-info/METADATA
boostedblob-1.0.0.dist-info/RECORD
