Metadata-Version: 2.4
Name: boostedblob
Version: 1.0.0
Summary: Command line tool and async library to perform basic file operations on local paths, Google Cloud Storage paths and Azure Blob Storage paths.
Author-email: Shantanu Jain <hauntsaninja@gmail.com>
Requires-Python: >=3.10
License-Expression: MIT
Requires-Dist: aiohttp>=3.7.2
Requires-Dist: lxml>=4.9.1
Requires-Dist: pycryptodomex>=3.9
Requires-Dist: uvloop>=0.16.0 ; sys_platform != 'win32'
